LICENSE
MANIFEST.in
README.md
package.json
setup.py
zdc/MyButton.py
zdc/MyTree.py
zdc/Zdc.py
zdc/__init__.py
zdc/_imports_.py
zdc/metadata.json
zdc/package-info.json
zdc/zdc.min.js
zdc/zdc.min.js.map
zdc.egg-info/PKG-INFO
zdc.egg-info/SOURCES.txt
zdc.egg-info/dependency_links.txt
zdc.egg-info/top_level.txt