Metadata-Version: 1.1
Name: zdc
Version: 0.0.2
Summary: Custom component from antd
Home-page: UNKNOWN
Author: hy zhang <309084102@qq.com>
Author-email: UNKNOWN
License: MIT
Platform: UNKNOWN
Classifier: Framework :: Dash
